just_kit/__init__.py
just_kit/auth.py
just_kit/services/__init__.py
just_kit/services/epay.py
just_kit/services/graduate.py
just_kit/services/health_check.py
just_kit/services/service.py
just_kit/utils/__init__.py
just_kit/utils/rajax.py
just_kit/utils/rsa.py
just_kit/utils/url.py
tests/__init__.py
tests/test_features.py
just_kit-0.2.3.dist-info/METADATA
just_kit-0.2.3.dist-info/WHEEL
just_kit-0.2.3.dist-info/top_level.txt
just_kit-0.2.3.dist-info/RECORD
