Metadata-Version: 2.4
Name: just_kit
Version: 0.2.3
Summary: 江苏科技大学信息门户工具包
Home-page: https://github.com/heerheer/just-kit
Author: Harmog
Author-email: harmog@foxmail.com
Requires-Dist: requests
Requires-Dist: beautifulsoup4
Requires-Dist: dotenv
Requires-Dist: pycryptodome
Dynamic: author
Dynamic: author-email
Dynamic: description
Dynamic: description-content-type
Dynamic: home-page
Dynamic: requires-dist
Dynamic: summary
